cxr_models/__init__.py
cxr_models/__version__.py
cxr_models/models_factory.py
cxr_models/tfkeras.py
cxr_models/models/__init__.py
cxr_models/models/blocks.py
cxr_models/models/covxnet.py
cxr_models-1.0.0.dist-info/LICENSE.md
cxr_models-1.0.0.dist-info/METADATA
cxr_models-1.0.0.dist-info/WHEEL
cxr_models-1.0.0.dist-info/top_level.txt
cxr_models-1.0.0.dist-info/RECORD
